<?xml version="1.0" encoding="utf-8"?>
<abapGit version="v1.0.0" serializer="LCL_OBJECT_IWPR" serializer_version="v1.0.0">
 <asx:abap xmlns:asx="http://www.sap.com/abapxml" version="1.0">
  <asx:values>
   <_-IWBEP_-I_SBD_AT>
    <_-IWBEP_-I_SBD_AT>
     <PROJECT>Z_DUMMY_ODATA</PROJECT>
     <NODE_UUID>AA06AMoaHumE6rA3B1YC+g==</NODE_UUID>
     <NODE_UUID_PA>AA06AMoaHumE6otdLq2C0w==</NODE_UUID_PA>
     <PLUGIN_PA>/IWBEP/CORE</PLUGIN_PA>
     <NODE_TYPE_PA>PROJ</NODE_TYPE_PA>
     <NAME>GENERATED_METHODS_RDS</NAME>
     <TYPE>V2_RDS</TYPE>
     <MIME_TYPE>XML</MIME_TYPE>
     <VALUE>PD94bWwgdmVyc2lvbj0iMS4wIiBlbmNvZGluZz0idXRmLTgiPz48YXN4OmFiYXAgdmVyc2lvbj0i
MS4wIiB4bWxuczphc3g9Imh0dHA6Ly93d3cuc2FwLmNvbS9hYmFweG1sIj48YXN4OnZhbHVlcz48
R0VOLz48L2FzeDp2YWx1ZXM+PC9hc3g6YWJhcD4=</VALUE>
    </_-IWBEP_-I_SBD_AT>
   </_-IWBEP_-I_SBD_AT>
   <_-IWBEP_-I_SBD_DS>
    <_-IWBEP_-I_SBD_DS>
     <PROJECT>Z_DUMMY_ODATA</PROJECT>
     <NODE_UUID>AA06AMoaHumE6o5WbnzC1Q==</NODE_UUID>
     <PARENT_UUID>AA06AMoaHumE6otdLq3C0w==</PARENT_UUID>
     <DS_TYPE>2</DS_TYPE>
     <RFC_DEST>SM1CLNT001</RFC_DEST>
    </_-IWBEP_-I_SBD_DS>
    <_-IWBEP_-I_SBD_DS>
     <PROJECT>Z_DUMMY_ODATA</PROJECT>
     <NODE_UUID>AA06AMoaHumE6p8CJ7bC6A==</NODE_UUID>
     <PARENT_UUID>AA06AMoaHumE6otdLq3C0w==</PARENT_UUID>
     <NAME>Z_DUMMY</NAME>
     <DS_GROUP>ZFM_TEST</DS_GROUP>
     <DS_TYPE>2</DS_TYPE>
     <RFC_DEST>SM1CLNT001</RFC_DEST>
     <FUNCTION_NAME>Z_DUMMY</FUNCTION_NAME>
    </_-IWBEP_-I_SBD_DS>
   </_-IWBEP_-I_SBD_DS>
   <_-IWBEP_-I_SBD_DST>
    <_-IWBEP_-I_SBD_DST>
     <SYLANGU>E</SYLANGU>
     <PROJECT>Z_DUMMY_ODATA</PROJECT>
     <NODE_UUID>AA06AMoaHumE6o5WbnzC1Q==</NODE_UUID>
    </_-IWBEP_-I_SBD_DST>
    <_-IWBEP_-I_SBD_DST>
     <SYLANGU>E</SYLANGU>
     <PROJECT>Z_DUMMY_ODATA</PROJECT>
     <NODE_UUID>AA06AMoaHumE6p8CJ7bC6A==</NODE_UUID>
     <DESCRIPTION>odata test fm</DESCRIPTION>
    </_-IWBEP_-I_SBD_DST>
   </_-IWBEP_-I_SBD_DST>
   <_-IWBEP_-I_SBD_GA>
    <_-IWBEP_-I_SBD_GA>
     <PROJECT>Z_DUMMY_ODATA</PROJECT>
     <NODE_UUID>AA06AMoaHumE6rA3B1Zi+g==</NODE_UUID>
     <CREATION_USER_ID>51705567</CREATION_USER_ID>
     <CREATION_TIME>20190108145553.837776</CREATION_TIME>
     <NAME>ZCL_Z_DUMMY_ODATA_MPC</NAME>
     <PGMID>R3TR</PGMID>
     <TROBJ_TYPE>CLAS</TROBJ_TYPE>
     <TROBJ_NAME>ZCL_Z_DUMMY_ODATA_MPC</TROBJ_NAME>
     <GEN_ART_TYPE>MPCB</GEN_ART_TYPE>
    </_-IWBEP_-I_SBD_GA>
    <_-IWBEP_-I_SBD_GA>
     <PROJECT>Z_DUMMY_ODATA</PROJECT>
     <NODE_UUID>AA06AMoaHumE6rA3B1aC+g==</NODE_UUID>
     <CREATION_USER_ID>51705567</CREATION_USER_ID>
     <CREATION_TIME>20190108145553.837783</CREATION_TIME>
     <NAME>ZCL_Z_DUMMY_ODATA_MPC_EXT</NAME>
     <PGMID>R3TR</PGMID>
     <TROBJ_TYPE>CLAS</TROBJ_TYPE>
     <TROBJ_NAME>ZCL_Z_DUMMY_ODATA_MPC_EXT</TROBJ_NAME>
     <GEN_ART_TYPE>MPCS</GEN_ART_TYPE>
    </_-IWBEP_-I_SBD_GA>
    <_-IWBEP_-I_SBD_GA>
     <PROJECT>Z_DUMMY_ODATA</PROJECT>
     <NODE_UUID>AA06AMoaHumE6rA3B1ai+g==</NODE_UUID>
     <CREATION_USER_ID>51705567</CREATION_USER_ID>
     <CREATION_TIME>20190108145555.991625</CREATION_TIME>
     <NAME>ZCL_Z_DUMMY_ODATA_DPC</NAME>
     <PGMID>R3TR</PGMID>
     <TROBJ_TYPE>CLAS</TROBJ_TYPE>
     <TROBJ_NAME>ZCL_Z_DUMMY_ODATA_DPC</TROBJ_NAME>
     <GEN_ART_TYPE>DPCB</GEN_ART_TYPE>
    </_-IWBEP_-I_SBD_GA>
    <_-IWBEP_-I_SBD_GA>
     <PROJECT>Z_DUMMY_ODATA</PROJECT>
     <NODE_UUID>AA06AMoaHumE6rA3B1bC+g==</NODE_UUID>
     <CREATION_USER_ID>51705567</CREATION_USER_ID>
     <CREATION_TIME>20190108145557.192787</CREATION_TIME>
     <NAME>ZCL_Z_DUMMY_ODATA_DPC_EXT</NAME>
     <PGMID>R3TR</PGMID>
     <TROBJ_TYPE>CLAS</TROBJ_TYPE>
     <TROBJ_NAME>ZCL_Z_DUMMY_ODATA_DPC_EXT</TROBJ_NAME>
     <GEN_ART_TYPE>DPCS</GEN_ART_TYPE>
    </_-IWBEP_-I_SBD_GA>
    <_-IWBEP_-I_SBD_GA>
     <PROJECT>Z_DUMMY_ODATA</PROJECT>
     <NODE_UUID>AA06AMoaHumE6rA3B1bi+g==</NODE_UUID>
     <CREATION_USER_ID>51705567</CREATION_USER_ID>
     <CREATION_TIME>20190108145558.801568</CREATION_TIME>
     <NAME>Z_DUMMY_ODATA_MDL</NAME>
     <PGMID>R3TR</PGMID>
     <TROBJ_TYPE>IWMO</TROBJ_TYPE>
     <TROBJ_NAME>Z_DUMMY_ODATA_MDL</TROBJ_NAME>
     <GEN_ART_TYPE>MDL</GEN_ART_TYPE>
    </_-IWBEP_-I_SBD_GA>
    <_-IWBEP_-I_SBD_GA>
     <PROJECT>Z_DUMMY_ODATA</PROJECT>
     <NODE_UUID>AA06AMoaHumE6rA3B1cC+g==</NODE_UUID>
     <CREATION_USER_ID>51705567</CREATION_USER_ID>
     <CREATION_TIME>20190108145558.801573</CREATION_TIME>
     <NAME>Z_DUMMY_ODATA_SRV</NAME>
     <PGMID>R3TR</PGMID>
     <TROBJ_TYPE>IWSV</TROBJ_TYPE>
     <TROBJ_NAME>Z_DUMMY_ODATA_SRV</TROBJ_NAME>
     <GEN_ART_TYPE>SRV</GEN_ART_TYPE>
    </_-IWBEP_-I_SBD_GA>
   </_-IWBEP_-I_SBD_GA>
   <_-IWBEP_-I_SBD_GAT>
    <_-IWBEP_-I_SBD_GAT>
     <SYLANGU>E</SYLANGU>
     <PROJECT>Z_DUMMY_ODATA</PROJECT>
     <NODE_UUID>AA06AMoaHumE6rA3B1Zi+g==</NODE_UUID>
    </_-IWBEP_-I_SBD_GAT>
    <_-IWBEP_-I_SBD_GAT>
     <SYLANGU>E</SYLANGU>
     <PROJECT>Z_DUMMY_ODATA</PROJECT>
     <NODE_UUID>AA06AMoaHumE6rA3B1aC+g==</NODE_UUID>
    </_-IWBEP_-I_SBD_GAT>
    <_-IWBEP_-I_SBD_GAT>
     <SYLANGU>E</SYLANGU>
     <PROJECT>Z_DUMMY_ODATA</PROJECT>
     <NODE_UUID>AA06AMoaHumE6rA3B1ai+g==</NODE_UUID>
    </_-IWBEP_-I_SBD_GAT>
    <_-IWBEP_-I_SBD_GAT>
     <SYLANGU>E</SYLANGU>
     <PROJECT>Z_DUMMY_ODATA</PROJECT>
     <NODE_UUID>AA06AMoaHumE6rA3B1bC+g==</NODE_UUID>
    </_-IWBEP_-I_SBD_GAT>
    <_-IWBEP_-I_SBD_GAT>
     <SYLANGU>E</SYLANGU>
     <PROJECT>Z_DUMMY_ODATA</PROJECT>
     <NODE_UUID>AA06AMoaHumE6rA3B1bi+g==</NODE_UUID>
    </_-IWBEP_-I_SBD_GAT>
    <_-IWBEP_-I_SBD_GAT>
     <SYLANGU>E</SYLANGU>
     <PROJECT>Z_DUMMY_ODATA</PROJECT>
     <NODE_UUID>AA06AMoaHumE6rA3B1cC+g==</NODE_UUID>
    </_-IWBEP_-I_SBD_GAT>
   </_-IWBEP_-I_SBD_GAT>
   <_-IWBEP_-I_SBD_MD>
    <_-IWBEP_-I_SBD_MD>
     <PROJECT>Z_DUMMY_ODATA</PROJECT>
     <NODE_UUID>AA06AMoaHumE6otdLq2i0w==</NODE_UUID>
     <NODE_UUID_PA>AA06AMoaHumE6otdLq2C0w==</NODE_UUID_PA>
     <PLUGIN_PA>/IWBEP/CORE</PLUGIN_PA>
     <NODE_TYPE_PA>PROJ</NODE_TYPE_PA>
     <TECHNICAL_NAME>Z_DUMMY_ODATA_MDL</TECHNICAL_NAME>
     <VERSION>0001</VERSION>
     <MPC>ZCL_Z_DUMMY_ODATA_MPC_EXT</MPC>
     <STATE_NS>S</STATE_NS>
     <VALUE_NS>Z_DUMMY_ODATA_SRV</VALUE_NS>
    </_-IWBEP_-I_SBD_MD>
   </_-IWBEP_-I_SBD_MD>
   <_-IWBEP_-I_SBD_MDT>
    <_-IWBEP_-I_SBD_MDT>
     <SYLANGU>E</SYLANGU>
     <PROJECT>Z_DUMMY_ODATA</PROJECT>
     <NODE_UUID>AA06AMoaHumE6otdLq2i0w==</NODE_UUID>
    </_-IWBEP_-I_SBD_MDT>
   </_-IWBEP_-I_SBD_MDT>
   <_-IWBEP_-I_SBD_NOI>
    <_-IWBEP_-I_SBD_NOI>
     <PROJECT>Z_DUMMY_ODATA</PROJECT>
     <NODE_UUID>AA06AMoaHumE6otdLq2C0w==</NODE_UUID>
    </_-IWBEP_-I_SBD_NOI>
    <_-IWBEP_-I_SBD_NOI>
     <PROJECT>Z_DUMMY_ODATA</PROJECT>
     <NODE_UUID>AA06AMoaHumE6otdLq2i0w==</NODE_UUID>
    </_-IWBEP_-I_SBD_NOI>
    <_-IWBEP_-I_SBD_NOI>
     <PROJECT>Z_DUMMY_ODATA</PROJECT>
     <NODE_UUID>AA06AMoaHumE6otdLq3C0w==</NODE_UUID>
    </_-IWBEP_-I_SBD_NOI>
    <_-IWBEP_-I_SBD_NOI>
     <PROJECT>Z_DUMMY_ODATA</PROJECT>
     <NODE_UUID>AA06AMoaHumE6o5WbnzC1Q==</NODE_UUID>
    </_-IWBEP_-I_SBD_NOI>
    <_-IWBEP_-I_SBD_NOI>
     <PROJECT>Z_DUMMY_ODATA</PROJECT>
     <NODE_UUID>AA06AMoaHumE6p8CJ7bC6A==</NODE_UUID>
    </_-IWBEP_-I_SBD_NOI>
    <_-IWBEP_-I_SBD_NOI>
     <PROJECT>Z_DUMMY_ODATA</PROJECT>
     <NODE_UUID>AA06AMoaHumE6qQ471PC7Q==</NODE_UUID>
     <TYPE>DASO</TYPE>
     <NAME>000D3A00CA1A1EE984EA9F0227B6C2E8</NAME>
    </_-IWBEP_-I_SBD_NOI>
    <_-IWBEP_-I_SBD_NOI>
     <PROJECT>Z_DUMMY_ODATA</PROJECT>
     <NODE_UUID>AA06AMoaHumE6qQ471Pi7Q==</NODE_UUID>
     <TYPE>DASO</TYPE>
     <NAME>000D3A00CA1A1EE984EA9F0227B6C2E8ET_DUMP_DET\SYDATE</NAME>
    </_-IWBEP_-I_SBD_NOI>
    <_-IWBEP_-I_SBD_NOI>
     <PROJECT>Z_DUMMY_ODATA</PROJECT>
     <NODE_UUID>AA06AMoaHumE6qQ471QC7Q==</NODE_UUID>
     <TYPE>DASO</TYPE>
     <NAME>000D3A00CA1A1EE984EA9F0227B6C2E8ET_DUMP_DET\SYTIME</NAME>
    </_-IWBEP_-I_SBD_NOI>
    <_-IWBEP_-I_SBD_NOI>
     <PROJECT>Z_DUMMY_ODATA</PROJECT>
     <NODE_UUID>AA06AMoaHumE6qQ471Qi7Q==</NODE_UUID>
     <TYPE>DASO</TYPE>
     <NAME>000D3A00CA1A1EE984EA9F0227B6C2E8ET_DUMP_DET\SYHOST</NAME>
    </_-IWBEP_-I_SBD_NOI>
    <_-IWBEP_-I_SBD_NOI>
     <PROJECT>Z_DUMMY_ODATA</PROJECT>
     <NODE_UUID>AA06AMoaHumE6qQ471RC7Q==</NODE_UUID>
     <TYPE>DASO</TYPE>
     <NAME>000D3A00CA1A1EE984EA9F0227B6C2E8ET_DUMP_DET\SYUSER</NAME>
    </_-IWBEP_-I_SBD_NOI>
    <_-IWBEP_-I_SBD_NOI>
     <PROJECT>Z_DUMMY_ODATA</PROJECT>
     <NODE_UUID>AA06AMoaHumE6qQ471Ri7Q==</NODE_UUID>
     <TYPE>DASO</TYPE>
     <NAME>000D3A00CA1A1EE984EA9F0227B6C2E8ET_DUMP_DET\DUMPID</NAME>
    </_-IWBEP_-I_SBD_NOI>
    <_-IWBEP_-I_SBD_NOI>
     <PROJECT>Z_DUMMY_ODATA</PROJECT>
     <NODE_UUID>AA06AMoaHumE6qQ471SC7Q==</NODE_UUID>
     <TYPE>DASO</TYPE>
     <NAME>000D3A00CA1A1EE984EA9F0227B6C2E8ET_DUMP_DET\PROGRAMNAME</NAME>
    </_-IWBEP_-I_SBD_NOI>
    <_-IWBEP_-I_SBD_NOI>
     <PROJECT>Z_DUMMY_ODATA</PROJECT>
     <NODE_UUID>AA06AMoaHumE6qQ471Si7Q==</NODE_UUID>
     <TYPE>DASO</TYPE>
     <NAME>000D3A00CA1A1EE984EA9F0227B6C2E8ET_DUMP_DET\INCLUDENAME</NAME>
    </_-IWBEP_-I_SBD_NOI>
    <_-IWBEP_-I_SBD_NOI>
     <PROJECT>Z_DUMMY_ODATA</PROJECT>
     <NODE_UUID>AA06AMoaHumE6qQ471TC7Q==</NODE_UUID>
     <TYPE>DASO</TYPE>
     <NAME>000D3A00CA1A1EE984EA9F0227B6C2E8ET_DUMP_DET\LINENUMBER</NAME>
    </_-IWBEP_-I_SBD_NOI>
    <_-IWBEP_-I_SBD_NOI>
     <PROJECT>Z_DUMMY_ODATA</PROJECT>
     <NODE_UUID>AA06AMoaHumE6qQ471Ti7Q==</NODE_UUID>
    </_-IWBEP_-I_SBD_NOI>
    <_-IWBEP_-I_SBD_NOI>
     <PROJECT>Z_DUMMY_ODATA</PROJECT>
     <NODE_UUID>AA06AMoaHumE6qQ471UC7Q==</NODE_UUID>
    </_-IWBEP_-I_SBD_NOI>
    <_-IWBEP_-I_SBD_NOI>
     <PROJECT>Z_DUMMY_ODATA</PROJECT>
     <NODE_UUID>AA06AMoaHumE6qQ471Ui7Q==</NODE_UUID>
    </_-IWBEP_-I_SBD_NOI>
    <_-IWBEP_-I_SBD_NOI>
     <PROJECT>Z_DUMMY_ODATA</PROJECT>
     <NODE_UUID>AA06AMoaHumE6qQ471VC7Q==</NODE_UUID>
    </_-IWBEP_-I_SBD_NOI>
    <_-IWBEP_-I_SBD_NOI>
     <PROJECT>Z_DUMMY_ODATA</PROJECT>
     <NODE_UUID>AA06AMoaHumE6qQ471Vi7Q==</NODE_UUID>
    </_-IWBEP_-I_SBD_NOI>
    <_-IWBEP_-I_SBD_NOI>
     <PROJECT>Z_DUMMY_ODATA</PROJECT>
     <NODE_UUID>AA06AMoaHumE6qQ471WC7Q==</NODE_UUID>
    </_-IWBEP_-I_SBD_NOI>
    <_-IWBEP_-I_SBD_NOI>
     <PROJECT>Z_DUMMY_ODATA</PROJECT>
     <NODE_UUID>AA06AMoaHumE6qQ471Wi7Q==</NODE_UUID>
    </_-IWBEP_-I_SBD_NOI>
    <_-IWBEP_-I_SBD_NOI>
     <PROJECT>Z_DUMMY_ODATA</PROJECT>
     <NODE_UUID>AA06AMoaHumE6rA3B1YC+g==</NODE_UUID>
    </_-IWBEP_-I_SBD_NOI>
    <_-IWBEP_-I_SBD_NOI>
     <PROJECT>Z_DUMMY_ODATA</PROJECT>
     <NODE_UUID>AA06AMoaHumE6rA3B1Zi+g==</NODE_UUID>
    </_-IWBEP_-I_SBD_NOI>
    <_-IWBEP_-I_SBD_NOI>
     <PROJECT>Z_DUMMY_ODATA</PROJECT>
     <NODE_UUID>AA06AMoaHumE6rA3B1aC+g==</NODE_UUID>
    </_-IWBEP_-I_SBD_NOI>
    <_-IWBEP_-I_SBD_NOI>
     <PROJECT>Z_DUMMY_ODATA</PROJECT>
     <NODE_UUID>AA06AMoaHumE6rA3B1ai+g==</NODE_UUID>
    </_-IWBEP_-I_SBD_NOI>
    <_-IWBEP_-I_SBD_NOI>
     <PROJECT>Z_DUMMY_ODATA</PROJECT>
     <NODE_UUID>AA06AMoaHumE6rA3B1bC+g==</NODE_UUID>
    </_-IWBEP_-I_SBD_NOI>
    <_-IWBEP_-I_SBD_NOI>
     <PROJECT>Z_DUMMY_ODATA</PROJECT>
     <NODE_UUID>AA06AMoaHumE6rA3B1bi+g==</NODE_UUID>
    </_-IWBEP_-I_SBD_NOI>
    <_-IWBEP_-I_SBD_NOI>
     <PROJECT>Z_DUMMY_ODATA</PROJECT>
     <NODE_UUID>AA06AMoaHumE6rA3B1cC+g==</NODE_UUID>
    </_-IWBEP_-I_SBD_NOI>
   </_-IWBEP_-I_SBD_NOI>
   <_-IWBEP_-I_SBD_OP>
    <_-IWBEP_-I_SBD_OP>
     <PROJECT>Z_DUMMY_ODATA</PROJECT>
     <NODE_UUID>AA06AMoaHumE6qQ471Ui7Q==</NODE_UUID>
     <PARENT_UUID>AA06AMoaHumE6qQ471UC7Q==</PARENT_UUID>
     <NAME>Create</NAME>
     <OPERATION_TYPE>C</OPERATION_TYPE>
     <IMP_METHOD>DUMPSET_CREATE_ENTITY</IMP_METHOD>
    </_-IWBEP_-I_SBD_OP>
    <_-IWBEP_-I_SBD_OP>
     <PROJECT>Z_DUMMY_ODATA</PROJECT>
     <NODE_UUID>AA06AMoaHumE6qQ471VC7Q==</NODE_UUID>
     <PARENT_UUID>AA06AMoaHumE6qQ471UC7Q==</PARENT_UUID>
     <NAME>GetEntity (Read)</NAME>
     <OPERATION_TYPE>R</OPERATION_TYPE>
     <IMP_METHOD>DUMPSET_GET_ENTITY</IMP_METHOD>
    </_-IWBEP_-I_SBD_OP>
    <_-IWBEP_-I_SBD_OP>
     <PROJECT>Z_DUMMY_ODATA</PROJECT>
     <NODE_UUID>AA06AMoaHumE6qQ471Vi7Q==</NODE_UUID>
     <PARENT_UUID>AA06AMoaHumE6qQ471UC7Q==</PARENT_UUID>
     <NAME>Update</NAME>
     <OPERATION_TYPE>U</OPERATION_TYPE>
     <IMP_METHOD>DUMPSET_UPDATE_ENTITY</IMP_METHOD>
    </_-IWBEP_-I_SBD_OP>
    <_-IWBEP_-I_SBD_OP>
     <PROJECT>Z_DUMMY_ODATA</PROJECT>
     <NODE_UUID>AA06AMoaHumE6qQ471WC7Q==</NODE_UUID>
     <PARENT_UUID>AA06AMoaHumE6qQ471UC7Q==</PARENT_UUID>
     <NAME>Delete</NAME>
     <OPERATION_TYPE>D</OPERATION_TYPE>
     <IMP_METHOD>DUMPSET_DELETE_ENTITY</IMP_METHOD>
    </_-IWBEP_-I_SBD_OP>
    <_-IWBEP_-I_SBD_OP>
     <PROJECT>Z_DUMMY_ODATA</PROJECT>
     <NODE_UUID>AA06AMoaHumE6qQ471Wi7Q==</NODE_UUID>
     <PARENT_UUID>AA06AMoaHumE6qQ471UC7Q==</PARENT_UUID>
     <NAME>GetEntitySet (Query)</NAME>
     <OPERATION_TYPE>Q</OPERATION_TYPE>
     <IMP_METHOD>DUMPSET_GET_ENTITYSET</IMP_METHOD>
    </_-IWBEP_-I_SBD_OP>
   </_-IWBEP_-I_SBD_OP>
   <_-IWBEP_-I_SBD_OPT>
    <_-IWBEP_-I_SBD_OPT>
     <SYLANGU>E</SYLANGU>
     <PROJECT>Z_DUMMY_ODATA</PROJECT>
     <NODE_UUID>AA06AMoaHumE6qQ471Ui7Q==</NODE_UUID>
    </_-IWBEP_-I_SBD_OPT>
    <_-IWBEP_-I_SBD_OPT>
     <SYLANGU>E</SYLANGU>
     <PROJECT>Z_DUMMY_ODATA</PROJECT>
     <NODE_UUID>AA06AMoaHumE6qQ471VC7Q==</NODE_UUID>
    </_-IWBEP_-I_SBD_OPT>
    <_-IWBEP_-I_SBD_OPT>
     <SYLANGU>E</SYLANGU>
     <PROJECT>Z_DUMMY_ODATA</PROJECT>
     <NODE_UUID>AA06AMoaHumE6qQ471Vi7Q==</NODE_UUID>
    </_-IWBEP_-I_SBD_OPT>
    <_-IWBEP_-I_SBD_OPT>
     <SYLANGU>E</SYLANGU>
     <PROJECT>Z_DUMMY_ODATA</PROJECT>
     <NODE_UUID>AA06AMoaHumE6qQ471WC7Q==</NODE_UUID>
    </_-IWBEP_-I_SBD_OPT>
    <_-IWBEP_-I_SBD_OPT>
     <SYLANGU>E</SYLANGU>
     <PROJECT>Z_DUMMY_ODATA</PROJECT>
     <NODE_UUID>AA06AMoaHumE6qQ471Wi7Q==</NODE_UUID>
    </_-IWBEP_-I_SBD_OPT>
   </_-IWBEP_-I_SBD_OPT>
   <_-IWBEP_-I_SBD_PR>
    <_-IWBEP_-I_SBD_PR>
     <PROJECT>Z_DUMMY_ODATA</PROJECT>
     <NODE_UUID>AA06AMoaHumE6otdLq2C0w==</NODE_UUID>
     <CREATION_USER_ID>51705567</CREATION_USER_ID>
     <CREATION_TIME>20190108144743.494245</CREATION_TIME>
     <LAST_CHG_USER_ID>51705567</LAST_CHG_USER_ID>
     <LAST_CHG_TIME>20190108145558.804226</LAST_CHG_TIME>
     <LAST_CHG_STATE>AA06AMoaHumE6rA3B1dC+g==</LAST_CHG_STATE>
     <PLUGIN>/IWBEP/GEN</PLUGIN>
     <STRAT_NAME>0001</STRAT_NAME>
     <STRAT_VERSION>0001</STRAT_VERSION>
     <PROJECT_TYPE>1</PROJECT_TYPE>
    </_-IWBEP_-I_SBD_PR>
   </_-IWBEP_-I_SBD_PR>
   <_-IWBEP_-I_SBD_PRT>
    <_-IWBEP_-I_SBD_PRT>
     <PROJECT>Z_DUMMY_ODATA</PROJECT>
     <SYLANGU>E</SYLANGU>
     <DESCRIPTION>odata for dumps</DESCRIPTION>
    </_-IWBEP_-I_SBD_PRT>
   </_-IWBEP_-I_SBD_PRT>
   <_-IWBEP_-I_SBD_SE>
    <_-IWBEP_-I_SBD_SE>
     <PROJECT>Z_DUMMY_ODATA</PROJECT>
     <NODE_UUID>AA06AMoaHumE6qQ471UC7Q==</NODE_UUID>
     <PARENT_UUID>AA06AMoaHumE6otdLq3C0w==</PARENT_UUID>
     <NAME>DUMPSet</NAME>
     <ENTITY_SET_UUID>AA06AMoaHumE6qQ471Ti7Q==</ENTITY_SET_UUID>
    </_-IWBEP_-I_SBD_SE>
   </_-IWBEP_-I_SBD_SE>
   <_-IWBEP_-I_SBD_SET>
    <_-IWBEP_-I_SBD_SET>
     <SYLANGU>E</SYLANGU>
     <PROJECT>Z_DUMMY_ODATA</PROJECT>
     <NODE_UUID>AA06AMoaHumE6qQ471UC7Q==</NODE_UUID>
    </_-IWBEP_-I_SBD_SET>
   </_-IWBEP_-I_SBD_SET>
   <_-IWBEP_-I_SBD_SV>
    <_-IWBEP_-I_SBD_SV>
     <PROJECT>Z_DUMMY_ODATA</PROJECT>
     <NODE_UUID>AA06AMoaHumE6otdLq3C0w==</NODE_UUID>
     <TECHNICAL_NAME>Z_DUMMY_ODATA_SRV</TECHNICAL_NAME>
     <VERSION>0001</VERSION>
     <DPC>ZCL_Z_DUMMY_ODATA_DPC_EXT</DPC>
     <EXTERNAL_NAME>Z_DUMMY_ODATA_SRV</EXTERNAL_NAME>
    </_-IWBEP_-I_SBD_SV>
   </_-IWBEP_-I_SBD_SV>
   <_-IWBEP_-I_SBD_SVT>
    <_-IWBEP_-I_SBD_SVT>
     <SYLANGU>E</SYLANGU>
     <PROJECT>Z_DUMMY_ODATA</PROJECT>
     <NODE_UUID>AA06AMoaHumE6otdLq3C0w==</NODE_UUID>
    </_-IWBEP_-I_SBD_SVT>
   </_-IWBEP_-I_SBD_SVT>
   <_-IWBEP_-I_SBO_ES>
    <_-IWBEP_-I_SBO_ES>
     <PROJECT>Z_DUMMY_ODATA</PROJECT>
     <NODE_UUID>AA06AMoaHumE6qQ471Ti7Q==</NODE_UUID>
     <MODEL>AA06AMoaHumE6otdLq2i0w==</MODEL>
     <NAME>dumpset</NAME>
     <ENTITY_TYPE>AA06AMoaHumE6qQ471PC7Q==</ENTITY_TYPE>
     <ADDRESSABLE>X</ADDRESSABLE>
     <REF_TYPE>T</REF_TYPE>
     <TECH_NAME>DUMPSET</TECH_NAME>
     <DESCRIPTION_XU>X</DESCRIPTION_XU>
     <IN_SERV_DOCU>X</IN_SERV_DOCU>
    </_-IWBEP_-I_SBO_ES>
   </_-IWBEP_-I_SBO_ES>
   <_-IWBEP_-I_SBO_EST>
    <_-IWBEP_-I_SBO_EST>
     <SYLANGU>E</SYLANGU>
     <PROJECT>Z_DUMMY_ODATA</PROJECT>
     <NODE_UUID>AA06AMoaHumE6qQ471Ti7Q==</NODE_UUID>
    </_-IWBEP_-I_SBO_EST>
   </_-IWBEP_-I_SBO_EST>
   <_-IWBEP_-I_SBO_ET>
    <_-IWBEP_-I_SBO_ET>
     <PROJECT>Z_DUMMY_ODATA</PROJECT>
     <NODE_UUID>AA06AMoaHumE6qQ471PC7Q==</NODE_UUID>
     <NAME>DUMP</NAME>
     <MODEL>AA06AMoaHumE6otdLq2i0w==</MODEL>
     <REF_TYPE>T</REF_TYPE>
     <TECH_NAME>DUMP</TECH_NAME>
     <BASE_TYPE_XU>X</BASE_TYPE_XU>
     <FC_TARGET_PATHXU>X</FC_TARGET_PATHXU>
     <ABAP_STRUCT_XU>X</ABAP_STRUCT_XU>
     <DESCRIPTION_XU>X</DESCRIPTION_XU>
    </_-IWBEP_-I_SBO_ET>
   </_-IWBEP_-I_SBO_ET>
   <_-IWBEP_-I_SBO_ETT>
    <_-IWBEP_-I_SBO_ETT>
     <SYLANGU>E</SYLANGU>
     <PROJECT>Z_DUMMY_ODATA</PROJECT>
     <NODE_UUID>AA06AMoaHumE6qQ471PC7Q==</NODE_UUID>
    </_-IWBEP_-I_SBO_ETT>
   </_-IWBEP_-I_SBO_ETT>
   <_-IWBEP_-I_SBO_PR>
    <_-IWBEP_-I_SBO_PR>
     <PROJECT>Z_DUMMY_ODATA</PROJECT>
     <NODE_UUID>AA06AMoaHumE6qQ471Pi7Q==</NODE_UUID>
     <PARENT_UUID>AA06AMoaHumE6qQ471PC7Q==</PARENT_UUID>
     <NAME>Sydate</NAME>
     <PROP_PRECISION>7</PROP_PRECISION>
     <EDM_CORE_TYPE>Edm.DateTime</EDM_CORE_TYPE>
     <REF_TYPE>T</REF_TYPE>
     <ABAP_FIELD>SYDATE</ABAP_FIELD>
     <TYPE_KIND>D</TYPE_KIND>
     <LENGTH>8</LENGTH>
     <AS_ETAG_XU>X</AS_ETAG_XU>
     <REQUIREFILTER_XU>X</REQUIREFILTER_XU>
     <UNIT_PROP_XU>X</UNIT_PROP_XU>
     <SORT_ORDER>1</SORT_ORDER>
     <DESCRIPTION_XU>X</DESCRIPTION_XU>
    </_-IWBEP_-I_SBO_PR>
    <_-IWBEP_-I_SBO_PR>
     <PROJECT>Z_DUMMY_ODATA</PROJECT>
     <NODE_UUID>AA06AMoaHumE6qQ471QC7Q==</NODE_UUID>
     <PARENT_UUID>AA06AMoaHumE6qQ471PC7Q==</PARENT_UUID>
     <NAME>Sytime</NAME>
     <EDM_CORE_TYPE>Edm.Time</EDM_CORE_TYPE>
     <REF_TYPE>T</REF_TYPE>
     <ABAP_FIELD>SYTIME</ABAP_FIELD>
     <AS_ETAG_XU>X</AS_ETAG_XU>
     <REQUIREFILTER_XU>X</REQUIREFILTER_XU>
     <UNIT_PROP_XU>X</UNIT_PROP_XU>
     <ABTY_XU>X</ABTY_XU>
     <SORT_ORDER>2</SORT_ORDER>
     <DESCRIPTION_XU>X</DESCRIPTION_XU>
    </_-IWBEP_-I_SBO_PR>
    <_-IWBEP_-I_SBO_PR>
     <PROJECT>Z_DUMMY_ODATA</PROJECT>
     <NODE_UUID>AA06AMoaHumE6qQ471Qi7Q==</NODE_UUID>
     <PARENT_UUID>AA06AMoaHumE6qQ471PC7Q==</PARENT_UUID>
     <NAME>Syhost</NAME>
     <MAX_LENGTH>32</MAX_LENGTH>
     <EDM_CORE_TYPE>Edm.String</EDM_CORE_TYPE>
     <REF_TYPE>T</REF_TYPE>
     <ABAP_FIELD>SYHOST</ABAP_FIELD>
     <AS_ETAG_XU>X</AS_ETAG_XU>
     <REQUIREFILTER_XU>X</REQUIREFILTER_XU>
     <UNIT_PROP_XU>X</UNIT_PROP_XU>
     <ABTY_XU>X</ABTY_XU>
     <SORT_ORDER>3</SORT_ORDER>
     <DESCRIPTION_XU>X</DESCRIPTION_XU>
    </_-IWBEP_-I_SBO_PR>
    <_-IWBEP_-I_SBO_PR>
     <PROJECT>Z_DUMMY_ODATA</PROJECT>
     <NODE_UUID>AA06AMoaHumE6qQ471RC7Q==</NODE_UUID>
     <PARENT_UUID>AA06AMoaHumE6qQ471PC7Q==</PARENT_UUID>
     <NAME>Syuser</NAME>
     <IS_KEY>X</IS_KEY>
     <MAX_LENGTH>12</MAX_LENGTH>
     <EDM_CORE_TYPE>Edm.String</EDM_CORE_TYPE>
     <REF_TYPE>T</REF_TYPE>
     <ABAP_FIELD>SYUSER</ABAP_FIELD>
     <AS_ETAG_XU>X</AS_ETAG_XU>
     <REQUIREFILTER_XU>X</REQUIREFILTER_XU>
     <UNIT_PROP_XU>X</UNIT_PROP_XU>
     <ABTY_XU>X</ABTY_XU>
     <SORT_ORDER>4</SORT_ORDER>
     <DESCRIPTION_XU>X</DESCRIPTION_XU>
    </_-IWBEP_-I_SBO_PR>
    <_-IWBEP_-I_SBO_PR>
     <PROJECT>Z_DUMMY_ODATA</PROJECT>
     <NODE_UUID>AA06AMoaHumE6qQ471Ri7Q==</NODE_UUID>
     <PARENT_UUID>AA06AMoaHumE6qQ471PC7Q==</PARENT_UUID>
     <NAME>Dumpid</NAME>
     <MAX_LENGTH>30</MAX_LENGTH>
     <EDM_CORE_TYPE>Edm.String</EDM_CORE_TYPE>
     <REF_TYPE>T</REF_TYPE>
     <ABAP_FIELD>DUMPID</ABAP_FIELD>
     <AS_ETAG_XU>X</AS_ETAG_XU>
     <REQUIREFILTER_XU>X</REQUIREFILTER_XU>
     <UNIT_PROP_XU>X</UNIT_PROP_XU>
     <ABTY_XU>X</ABTY_XU>
     <SORT_ORDER>5</SORT_ORDER>
     <DESCRIPTION_XU>X</DESCRIPTION_XU>
    </_-IWBEP_-I_SBO_PR>
    <_-IWBEP_-I_SBO_PR>
     <PROJECT>Z_DUMMY_ODATA</PROJECT>
     <NODE_UUID>AA06AMoaHumE6qQ471SC7Q==</NODE_UUID>
     <PARENT_UUID>AA06AMoaHumE6qQ471PC7Q==</PARENT_UUID>
     <NAME>Programname</NAME>
     <MAX_LENGTH>40</MAX_LENGTH>
     <EDM_CORE_TYPE>Edm.String</EDM_CORE_TYPE>
     <REF_TYPE>T</REF_TYPE>
     <ABAP_FIELD>PROGRAMNAME</ABAP_FIELD>
     <AS_ETAG_XU>X</AS_ETAG_XU>
     <REQUIREFILTER_XU>X</REQUIREFILTER_XU>
     <UNIT_PROP_XU>X</UNIT_PROP_XU>
     <ABTY_XU>X</ABTY_XU>
     <SORT_ORDER>6</SORT_ORDER>
     <DESCRIPTION_XU>X</DESCRIPTION_XU>
    </_-IWBEP_-I_SBO_PR>
    <_-IWBEP_-I_SBO_PR>
     <PROJECT>Z_DUMMY_ODATA</PROJECT>
     <NODE_UUID>AA06AMoaHumE6qQ471Si7Q==</NODE_UUID>
     <PARENT_UUID>AA06AMoaHumE6qQ471PC7Q==</PARENT_UUID>
     <NAME>Includename</NAME>
     <MAX_LENGTH>40</MAX_LENGTH>
     <EDM_CORE_TYPE>Edm.String</EDM_CORE_TYPE>
     <REF_TYPE>T</REF_TYPE>
     <ABAP_FIELD>INCLUDENAME</ABAP_FIELD>
     <AS_ETAG_XU>X</AS_ETAG_XU>
     <REQUIREFILTER_XU>X</REQUIREFILTER_XU>
     <UNIT_PROP_XU>X</UNIT_PROP_XU>
     <ABTY_XU>X</ABTY_XU>
     <SORT_ORDER>7</SORT_ORDER>
     <DESCRIPTION_XU>X</DESCRIPTION_XU>
    </_-IWBEP_-I_SBO_PR>
    <_-IWBEP_-I_SBO_PR>
     <PROJECT>Z_DUMMY_ODATA</PROJECT>
     <NODE_UUID>AA06AMoaHumE6qQ471TC7Q==</NODE_UUID>
     <PARENT_UUID>AA06AMoaHumE6qQ471PC7Q==</PARENT_UUID>
     <NAME>Linenumber</NAME>
     <MAX_LENGTH>5</MAX_LENGTH>
     <EDM_CORE_TYPE>Edm.String</EDM_CORE_TYPE>
     <REF_TYPE>T</REF_TYPE>
     <ABAP_FIELD>LINENUMBER</ABAP_FIELD>
     <AS_ETAG_XU>X</AS_ETAG_XU>
     <REQUIREFILTER_XU>X</REQUIREFILTER_XU>
     <UNIT_PROP_XU>X</UNIT_PROP_XU>
     <ABTY_XU>X</ABTY_XU>
     <SORT_ORDER>8</SORT_ORDER>
     <DESCRIPTION_XU>X</DESCRIPTION_XU>
    </_-IWBEP_-I_SBO_PR>
   </_-IWBEP_-I_SBO_PR>
   <_-IWBEP_-I_SBO_PRT>
    <_-IWBEP_-I_SBO_PRT>
     <SYLANGU>E</SYLANGU>
     <PROJECT>Z_DUMMY_ODATA</PROJECT>
     <NODE_UUID>AA06AMoaHumE6qQ471Pi7Q==</NODE_UUID>
     <PROP_LABEL>Current Date</PROP_LABEL>
    </_-IWBEP_-I_SBO_PRT>
    <_-IWBEP_-I_SBO_PRT>
     <SYLANGU>E</SYLANGU>
     <PROJECT>Z_DUMMY_ODATA</PROJECT>
     <NODE_UUID>AA06AMoaHumE6qQ471QC7Q==</NODE_UUID>
     <PROP_LABEL>Time</PROP_LABEL>
    </_-IWBEP_-I_SBO_PRT>
    <_-IWBEP_-I_SBO_PRT>
     <SYLANGU>E</SYLANGU>
     <PROJECT>Z_DUMMY_ODATA</PROJECT>
     <NODE_UUID>AA06AMoaHumE6qQ471Qi7Q==</NODE_UUID>
     <PROP_LABEL>App.Server</PROP_LABEL>
    </_-IWBEP_-I_SBO_PRT>
    <_-IWBEP_-I_SBO_PRT>
     <SYLANGU>E</SYLANGU>
     <PROJECT>Z_DUMMY_ODATA</PROJECT>
     <NODE_UUID>AA06AMoaHumE6qQ471RC7Q==</NODE_UUID>
     <PROP_LABEL>User Name</PROP_LABEL>
    </_-IWBEP_-I_SBO_PRT>
    <_-IWBEP_-I_SBO_PRT>
     <SYLANGU>E</SYLANGU>
     <PROJECT>Z_DUMMY_ODATA</PROJECT>
     <NODE_UUID>AA06AMoaHumE6qQ471Ri7Q==</NODE_UUID>
     <PROP_LABEL>Name of runtime error</PROP_LABEL>
    </_-IWBEP_-I_SBO_PRT>
    <_-IWBEP_-I_SBO_PRT>
     <SYLANGU>E</SYLANGU>
     <PROJECT>Z_DUMMY_ODATA</PROJECT>
     <NODE_UUID>AA06AMoaHumE6qQ471SC7Q==</NODE_UUID>
     <PROP_LABEL>Program Name</PROP_LABEL>
    </_-IWBEP_-I_SBO_PRT>
    <_-IWBEP_-I_SBO_PRT>
     <SYLANGU>E</SYLANGU>
     <PROJECT>Z_DUMMY_ODATA</PROJECT>
     <NODE_UUID>AA06AMoaHumE6qQ471Si7Q==</NODE_UUID>
     <PROP_LABEL>Program Name</PROP_LABEL>
    </_-IWBEP_-I_SBO_PRT>
    <_-IWBEP_-I_SBO_PRT>
     <SYLANGU>E</SYLANGU>
     <PROJECT>Z_DUMMY_ODATA</PROJECT>
     <NODE_UUID>AA06AMoaHumE6qQ471TC7Q==</NODE_UUID>
     <PROP_LABEL>Source code line of an ABAP/4 program</PROP_LABEL>
    </_-IWBEP_-I_SBO_PRT>
   </_-IWBEP_-I_SBO_PRT>
  </asx:values>
 </asx:abap>
</abapGit>
